odoo10_addon_website_blog_category-10.0.1.0.0-py2.7-nspkg.pth
odoo/addons/website_blog_category/README.rst
odoo/addons/website_blog_category/__init__.py
odoo/addons/website_blog_category/__manifest__.py
odoo/addons/website_blog_category/controllers/__init__.py
odoo/addons/website_blog_category/controllers/main.py
odoo/addons/website_blog_category/demo/assets_demo.xml
odoo/addons/website_blog_category/demo/blog_category_demo.xml
odoo/addons/website_blog_category/demo/blog_post_demo.xml
odoo/addons/website_blog_category/models/__init__.py
odoo/addons/website_blog_category/models/blog_blog.py
odoo/addons/website_blog_category/models/blog_category.py
odoo/addons/website_blog_category/models/blog_post.py
odoo/addons/website_blog_category/security/ir.model.access.csv
odoo/addons/website_blog_category/static/description/icon.png
odoo/addons/website_blog_category/static/test/js/website_blog_category.tour.js
odoo/addons/website_blog_category/templates/website_blog_template.xml
odoo/addons/website_blog_category/tests/__init__.py
odoo/addons/website_blog_category/tests/test_blog_category.py
odoo/addons/website_blog_category/tests/test_ui.py
odoo/addons/website_blog_category/views/blog_blog_view.xml
odoo/addons/website_blog_category/views/blog_category_view.xml
odoo/addons/website_blog_category/views/blog_post_view.xml
odoo10_addon_website_blog_category-10.0.1.0.0.dist-info/DESCRIPTION.rst
odoo10_addon_website_blog_category-10.0.1.0.0.dist-info/METADATA
odoo10_addon_website_blog_category-10.0.1.0.0.dist-info/RECORD
odoo10_addon_website_blog_category-10.0.1.0.0.dist-info/WHEEL
odoo10_addon_website_blog_category-10.0.1.0.0.dist-info/metadata.json
odoo10_addon_website_blog_category-10.0.1.0.0.dist-info/namespace_packages.txt
odoo10_addon_website_blog_category-10.0.1.0.0.dist-info/top_level.txt
